README
setup.cfg
setup.py
mci/__init__.py
mci/bridges.py
mci/bulbs.py
mci/mci_parser.py
mci.egg-info/PKG-INFO
mci.egg-info/SOURCES.txt
mci.egg-info/dependency_links.txt
mci.egg-info/entry_points.txt
mci.egg-info/top_level.txt
mci.egg-info/zip-safe