Metadata-Version: 1.1
Name: mci
Version: 1.1.1
Summary: MiLight-Control-Interface
Home-page: https://hanckmann.com
Author: Patrick Hanckmann
Author-email: hanckmann@gmail.com
License: GNU Lesser General Public License v2 (LGPLv2)
Keywords: milight led light interface
Platform: UNKNOWN
Classifier: Development Status :: 5 - Production/Stable
Classifier: Environment :: Console
Classifier: Intended Audience :: Other Audience
Classifier: License :: OSI Approved :: GNU Lesser General Public License v2 (LGPLv2)
Classifier: Natural Language :: English
Classifier: Operating System :: OS Independent
Classifier: Programming Language :: Python :: 3 :: Only
Classifier: Topic :: Home Automation
